.gitignore
CHANGES.txt
README.rst
bootstrap.py
buildout.cfg
setup.py
docs/INSTALL.txt
docs/LICENSE.GPL
docs/LICENSE.txt
transmogrify/__init__.py
transmogrify.ploneremote.egg-info/PKG-INFO
transmogrify.ploneremote.egg-info/SOURCES.txt
transmogrify.ploneremote.egg-info/dependency_links.txt
transmogrify.ploneremote.egg-info/entry_points.txt
transmogrify.ploneremote.egg-info/namespace_packages.txt
transmogrify.ploneremote.egg-info/not-zip-safe
transmogrify.ploneremote.egg-info/requires.txt
transmogrify.ploneremote.egg-info/top_level.txt
transmogrify/ploneremote/__init__.py
transmogrify/ploneremote/base.py
transmogrify/ploneremote/configure.zcml
transmogrify/ploneremote/ploneapi.py
transmogrify/ploneremote/remoteconstructor.py
transmogrify/ploneremote/remotenavigationexcluder.py
transmogrify/ploneremote/remoteportlets.py
transmogrify/ploneremote/remoteprune.py
transmogrify/ploneremote/remoteredirector.py
transmogrify/ploneremote/remoteschemaupdater.py
transmogrify/ploneremote/remoteworkflowupdater.py
transmogrify/ploneremote/tests.py
transmogrify/ploneremote/tests/__init__.py
transmogrify/ploneremote/tests/base.py
transmogrify/ploneremote/tests/test_doctests.py
transmogrify/ploneremote/tests/test_events.py
transmogrify/ploneremote/tests/test_setup.py
transmogrify/ploneremote/tests/test_storage.py
transmogrify/ploneremote/tests/test_view.py