Metadata-Version: 1.0
Name: transmogrify.ploneremote
Version: 1.3
Summary: Transmogrifier blueprints for uploading content
Home-page: http://github.com/collective/transmogrify.ploneremote
Author: Dylan Jay
Author-email: software@pretaweb.com
License: GPL
Keywords: transmogrifier blueprint funnelweb source plone import
Platform: UNKNOWN
Classifier: Programming Language :: Python
Classifier: Topic :: Software Development :: Libraries :: Python Modules
